autodistill_metaclip/__init__.py
autodistill_metaclip/metaclip_model.py
autodistill_metaclip-0.1.3.dist-info/LICENSE
autodistill_metaclip-0.1.3.dist-info/METADATA
autodistill_metaclip-0.1.3.dist-info/WHEEL
autodistill_metaclip-0.1.3.dist-info/top_level.txt
autodistill_metaclip-0.1.3.dist-info/RECORD
